{"frames": {

"+.png":
{
	"frame": {"x":0,"y":0,"w":236,"h":235},
	"rotated": false,
	"trimmed": false,
	"spriteSourceSize": {"x":0,"y":0,"w":236,"h":235},
	"sourceSize": {"w":236,"h":235}
},
"-.png":
{
	"frame": {"x":236,"y":0,"w":235,"h":235},
	"rotated": false,
	"trimmed": false,
	"spriteSourceSize": {"x":0,"y":0,"w":235,"h":235},
	"sourceSize": {"w":235,"h":235}
},
"r.png":
{
	"frame": {"x":471,"y":0,"w":235,"h":235},
	"rotated": false,
	"trimmed": false,
	"spriteSourceSize": {"x":0,"y":0,"w":235,"h":235},
	"sourceSize": {"w":235,"h":235}
},
"t.png":
{
	"frame": {"x":706,"y":0,"w":235,"h":235},
	"rotated": false,
	"trimmed": false,
	"spriteSourceSize": {"x":0,"y":0,"w":235,"h":235},
	"sourceSize": {"w":235,"h":235}
}},
"meta": {
	"app": "https://www.codeandweb.com/texturepacker",
	"version": "1.1",
	"image": "pipes_spritesheet.png",
	"format": "RGBA8888",
	"size": {"w":941,"h":235},
	"scale": "1",
	"smartupdate": "$TexturePacker:SmartUpdate:8329ec236c98a52576e9d1963eb9cbc4:04d2bdf650fa116cc3a627809c268cd4:28c4695117642656b06b723ba55cd009$"
}
}
